jellyfish/_jellyfish.py
jellyfish/__init__.py
jellyfish/test.py
jellyfish/cjellyfish.cpython-34m.so
jellyfish/porter.py
jellyfish_wheel-0.7.0.dist-info/RECORD
jellyfish_wheel-0.7.0.dist-info/WHEEL
jellyfish_wheel-0.7.0.dist-info/top_level.txt
jellyfish_wheel-0.7.0.dist-info/METADATA
