Metadata-Version: 2.1
Name: jellyfish-wheel
Version: 0.7.0
Summary: a library for doing approximate and phonetic matching of strings.
Home-page: http://github.com/jezeniel/jellyfish-wheel
Author: UNKNOWN
Author-email: UNKNOWN
License: UNKNOWN
Platform: any
Classifier: Development Status :: 4 - Beta
Classifier: Intended Audience :: Developers
Classifier: License :: OSI Approved :: BSD License
Classifier: Natural Language :: English
Classifier: Operating System :: OS Independent
Classifier: Programming Language :: Python :: 3.4
Classifier: Programming Language :: Python :: 3.5
Classifier: Programming Language :: Python :: 3.6
Classifier: Topic :: Text Processing :: Linguistic
